autoflow/__init__.py
autoflow/main.py
autoflow/py.typed
autoflow/schema.py
autoflow/chat/__init__.py
autoflow/datasources/__init__.py
autoflow/datasources/base.py
autoflow/datasources/file.py
autoflow/datasources/mime_types.py
autoflow/datasources/web_base.py
autoflow/datasources/web_single_page.py
autoflow/datasources/web_sitemap.py
autoflow/indices/__init__.py
autoflow/indices/fulltext_search/__init__.py
autoflow/indices/knowledge_graph/__init__.py
autoflow/indices/knowledge_graph/base.py
autoflow/indices/knowledge_graph/extractor.py
autoflow/indices/knowledge_graph/schema.py
autoflow/indices/vector_search/__init__.py
autoflow/indices/vector_search/base.py
autoflow/knowledge_base/__init__.py
autoflow/knowledge_base/base.py
autoflow/knowledge_base/config.py
autoflow/knowledge_base/datasource.py
autoflow/knowledge_base/manager.py
autoflow/llms/__init__.py
autoflow/llms/provider.py
autoflow/llms/chat_models/__init__.py
autoflow/llms/embeddings/__init__.py
autoflow/llms/embeddings/litellm.py
autoflow/llms/rerankers/__init__.py
autoflow/llms/rerankers/litellm.py
autoflow/models/__init__.py
autoflow/models/base.py
autoflow/models/chunk.py
autoflow/models/document.py
autoflow/models/entity.py
autoflow/models/relationship.py
autoflow/prompts/__init__.py
autoflow/prompts/default_prompt.py
autoflow/storage/__init__.py
autoflow/storage/schema.py
autoflow/storage/doc_store/__init__.py
autoflow/storage/doc_store/base.py
autoflow/storage/doc_store/postgres/TODO
autoflow/storage/doc_store/postgres/__init__.py
autoflow/storage/doc_store/tidb/__init__.py
autoflow/storage/doc_store/tidb/tidb_doc_store.py
autoflow/storage/graph_store/__init__.py
autoflow/storage/graph_store/base.py
autoflow/storage/graph_store/algorithms/__init__.py
autoflow/storage/graph_store/algorithms/base.py
autoflow/storage/graph_store/algorithms/weighted.py
autoflow/storage/graph_store/postgres/TODO
autoflow/storage/graph_store/postgres/__init__.py
autoflow/storage/graph_store/tidb/__init__.py
automem-0.0.1.dev1.dist-info/METADATA
automem-0.0.1.dev1.dist-info/WHEEL
automem-0.0.1.dev1.dist-info/RECORD
